{
  "gitSyncId": "6886fa708a78c04a4132ad3c_6c8168fe-0a93-449d-900e-75f29e9c3dd8",
  "id": "Manufacturing Editor_GetPlan",
  "pluginId": "postgres-plugin",
  "pluginType": "DB",
  "unpublishedAction": {
    "actionConfiguration": {
      "body": "SELECT\n    reference            AS order_ref,     -- unique ID in this table\n    item_id,\n    location_id,\n    startdate,\n    enddate,\n    quantity,\n    status\nFROM   public.operationplan\nWHERE  startdate >= {{ StartDate.selectedDate }}\n  AND  enddate   <= {{ EndDate.selectedDate }};\n",
      "encodeParamsToggle": true,
      "paginationType": "NONE",
      "pluginSpecifiedTemplates": [
        {
          "value": true
        }
      ],
      "timeoutInMillisecond": 10000
    },
    "confirmBeforeExecute": false,
    "datasource": {
      "id": "FrePPle Config",
      "isAutoGenerated": false,
      "name": "FrePPle Config",
      "pluginId": "postgres-plugin"
    },
    "dynamicBindingPathList": [
      {
        "key": "body"
      }
    ],
    "name": "GetPlan",
    "pageId": "Manufacturing Editor",
    "runBehaviour": "ON_PAGE_LOAD",
    "userSetOnLoad": false
  }
}